Workbook
Name volume_per_month: Inputs!$D$5
Name minutes_before: Inputs!$D$6
Name minutes_after: Inputs!$D$7
Name hourly_cost_eur: Inputs!$D$8
Name share_hours_redeployed: Inputs!$D$9
Name error_rate_before: Inputs!$D$10
Name error_rate_after: Inputs!$D$11
Name cost_per_error_eur: Inputs!$D$12
Name licence_cost_per_year_eur: Inputs!$D$13
Name build_days: Inputs!$D$14
Name day_rate_eur: Inputs!$D$15
Name other_one_off_eur: Inputs!$D$16
Name run_cost_per_year_eur: Inputs!$D$17
Name adoption_initial: Inputs!$D$18
Name ramp_months: Inputs!$D$19
Name adoption_steady: Inputs!$D$20
Name discount_rate: Inputs!$D$21

Sheet Read me
A1: Business case
A2: UC-01: Supplier delivery notes captured into the ERP without manual typing
A3: FICTIONAL EXAMPLE. All names and figures are invented for illustration ("Northwind Aero Services").
A6: How to use
A7: 1. Enter inputs on the 'Inputs' sheet (blue text on yellow = input). Everything else is a formula.
A8: 2. Enter the pessimistic and optimistic values of the three most uncertain inputs on 'Scenarios'.
A9: 3. Record the source and confidence of every input on 'Assumptions log'.
A10: 4. Read the results on 'Calculation'. 'Cash flow' shows the 36 months behind payback and NPV.
A12: Counting rules
A13: - A benefit counts only once. If the same saved hours or avoided errors appear in another use case, count them in one case only.
A14: - Hours saved are not cash. They count as cash only if they are redeployed to valued work or a cost is avoided (overtime, temporary staff, a planned hire). The share is an explicit input; the rest is shown as 'not counted'.
A15: - Benefits ramp up with adoption. Nothing starts at 100% on day one.
... A21: Nothing in this workbook is protected. Results are recalculated when the file is opened.

Sheet Inputs
A1: Inputs
A2: UC-01: Supplier delivery notes captured into the ERP without manual typing
A3: FICTIONAL EXAMPLE. All names and figures are invented for illustration ("Northwind Aero Services").
A4: Group | B4: ID (defined name) | C4: Input | D4: Value | E4: Unit
A5: Process | B5: volume_per_month | C5: Transactions per month | D5: 3000 | E5: delivery notes / month
A6: Process | B6: minutes_before | C6: Handling time per transaction today | D6: 6 | E6: minutes
A7: Process | B7: minutes_after | C7: Handling time per transaction with the AI solution | D7: 2 | E7: minutes (base; see Scenarios)
A8: Process | B8: hourly_cost_eur | C8: Fully loaded cost per hour | D8: 70 | E8: EUR / hour
A9: Process | B9: share_hours_redeployed | C9: Share of saved hours redeployed or avoiding a cost | D9: 0.5 | E9: share (0-1) (base; see Scenarios)
A10: Process | B10: error_rate_before | C10: Error rate today | D10: 0.03 | E10: share of transactions
A11: Process | B11: error_rate_after | C11: Error rate with the AI solution | D11: 0.01 | E11: share of transactions
A12: Process | B12: cost_per_error_eur | C12: Cost per error | D12: 50 | E12: EUR / error
A13: Costs | B13: licence_cost_per_year_eur | C13: Licence cost per year | D13: 18000 | E13: EUR / year
A14: Costs | B14: build_days | C14: Internal build effort | D14: 60 | E14: person-days
A15: Costs | B15: day_rate_eur | C15: Internal day rate | D15: 600 | E15: EUR / day
A16: Costs | B16: other_one_off_eur | C16: Other one-off costs | D16: 15000 | E16: EUR
... A21: Adoption and finance | B21: discount_rate | C21: Discount rate | D21: 0.08 | E21: per year

Sheet Scenarios
A1: Scenarios: the three most uncertain inputs
A2: UC-01: Supplier delivery notes captured into the ERP without manual typing
A3: FICTIONAL EXAMPLE. All names and figures are invented for illustration ("Northwind Aero Services").
A4: ID | B4: Input | C4: Pessimistic | D4: Base | E4: Optimistic | F4: Unit | G4: Why it is uncertain
A5: minutes_after | B5: Handling time per transaction with the AI solution | C5: 3 | D5: =Inputs!$D$7 | E5: 1.5 | F5: minutes | G5: Checking time depends on extraction quality across 400 supplier layouts.
A6: share_hours_redeployed | B6: Share of saved hours redeployed or avoiding a cost | C6: 0.25 | D6: =Inputs!$D$9 | E6: 0.75 | F6: share (0-1) | G6: Depends on whether the claims backlog really absorbs the freed time.
A7: adoption_steady | B7: Adoption after the ramp-up | C7: 0.6 | D7: =Inputs!$D$20 | E7: 0.9 | F7: share of volume | G7: Depends on how many suppliers send machine-readable PDFs.
A9: Base values come from the Inputs sheet. Change them there.

Sheet Calculation
A1: Calculation
A2: UC-01: Supplier delivery notes captured into the ERP without manual typing
A3: FICTIONAL EXAMPLE. All names and figures are invented for illustration ("Northwind Aero Services").
A4: Metric | B4: How it is calculated | C4: Pessimistic | D4: Base | E4: Optimistic
A5: Effective inputs
A6: Transactions per month | B6: Inputs sheet (same in all scenarios) | C6: =volume_per_month | D6: =volume_per_month | E6: =volume_per_month
A7: Handling time per transaction today | B7: Inputs sheet (same in all scenarios) | C7: =minutes_before | D7: =minutes_before | E7: =minutes_before
A8: Handling time per transaction with the AI solution | B8: Scenarios sheet | C8: =Scenarios!C5 | D8: =Scenarios!D5 | E8: =Scenarios!E5
A9: Fully loaded cost per hour | B9: Inputs sheet (same in all scenarios) | C9: =hourly_cost_eur | D9: =hourly_cost_eur | E9: =hourly_cost_eur
A10: Share of saved hours redeployed or avoiding a cost | B10: Scenarios sheet | C10: =Scenarios!C6 | D10: =Scenarios!D6 | E10: =Scenarios!E6
A11: Error rate today | B11: Inputs sheet (same in all scenarios) | C11: =error_rate_before | D11: =error_rate_before | E11: =error_rate_before
A12: Error rate with the AI solution | B12: Inputs sheet (same in all scenarios) | C12: =error_rate_after | D12: =error_rate_after | E12: =error_rate_after
A13: Cost per error | B13: Inputs sheet (same in all scenarios) | C13: =cost_per_error_eur | D13: =cost_per_error_eur | E13: =cost_per_error_eur
A14: Licence cost per year | B14: Inputs sheet (same in all scenarios) | C14: =licence_cost_per_year_eur | D14: =licence_cost_per_year_eur | E14: =licence_cost_per_year_eur
A15: Internal build effort | B15: Inputs sheet (same in all scenarios) | C15: =build_days | D15: =build_days | E15: =build_days
A16: Internal day rate | B16: Inputs sheet (same in all scenarios) | C16: =day_rate_eur | D16: =day_rate_eur | E16: =day_rate_eur
A17: Other one-off costs | B17: Inputs sheet (same in all scenarios) | C17: =other_one_off_eur | D17: =other_one_off_eur | E17: =other_one_off_eur
A18: Run cost per year | B18: Inputs sheet (same in all scenarios) | C18: =run_cost_per_year_eur | D18: =run_cost_per_year_eur | E18: =run_cost_per_year_eur
A19: Adoption during the ramp-up | B19: Inputs sheet (same in all scenarios) | C19: =adoption_initial | D19: =adoption_initial | E19: =adoption_initial
A20: Length of the ramp-up | B20: Inputs sheet (same in all scenarios) | C20: =ramp_months | D20: =ramp_months | E20: =ramp_months
A21: Adoption after the ramp-up | B21: Scenarios sheet | C21: =Scenarios!C7 | D21: =Scenarios!D7 | E21: =Scenarios!E7
A22: Discount rate | B22: Inputs sheet (same in all scenarios) | C22: =discount_rate | D22: =discount_rate | E22: =discount_rate
A24: Results
A25: Hours saved per month at full adoption | B25: volume x (minutes before - after) / 60 | C25: =C6*(C7-C8)/60 | D25: =D6*(D7-D8)/60 | E25: =E6*(E7-E8)/60
A26: of which counted as cash | B26: hours saved x share redeployed | C26: =C25*C10 | D26: =D25*D10 | E26: =E25*E10
A27: Cash value of redeployed hours per month | B27: hours counted as cash x hourly cost | C27: =C26*C9 | D27: =D26*D9 | E27: =E26*E9
A28: Errors avoided per month at full adoption | B28: volume x (error rate before - after) | C28: =C6*(C11-C12) | D28: =D6*(D11-D12) | E28: =E6*(E11-E12)
A29: Value of errors avoided per month | B29: errors avoided x cost per error | C29: =C28*C13 | D29: =D28*D13 | E29: =E28*E13
A30: Monthly benefit at full adoption | B30: cash value of hours + value of errors avoided | C30: =C27+C29 | D30: =D27+D29 | E30: =E27+E29
A31: Annual benefit at steady adoption | B31: 12 x monthly benefit x steady adoption | C31: =12*C30*C21 | D31: =12*D30*D21 | E31: =12*E30*E21
A32: One-off cost (month 0) | B32: build days x day rate + other one-off costs | C32: =C15*C16+C17 | D32: =D15*D16+D17 | E32: =E15*E16+E17
A33: Annual run cost | B33: licence + run cost per year | C33: =C14+C18 | D33: =D14+D18 | E33: =E14+E18
A34: Payback (months) | B34: first month with cumulative net cash flow >= 0 | C34: =IF(COUNT('Cash flow'!H5:H41)=0,"not within 36",MIN('Cash flow'!H5:H41)) | D34: =IF(COUNT('Cash flow'!O5:O41)=0,"not within 36",MIN('Cash flow'!O5:O41)) | E34: =IF(COUNT('Cash flow'!V5:V41)=0,"not within 36",MIN('Cash flow'!V5:V41))
A35: 3-year NPV | B35: sum of monthly net cash flows discounted at (1 + rate)^(month / 12) | C35: =SUM('Cash flow'!G5:G41) | D35: =SUM('Cash flow'!N5:N41) | E35: =SUM('Cash flow'!U5:U41)
A36: Total benefit over 3 years | B36: sum of monthly benefits | C36: =SUM('Cash flow'!C5:C41) | D36: =SUM('Cash flow'!J5:J41) | E36: =SUM('Cash flow'!Q5:Q41)
A37: Total cost over 3 years | B37: one-off + monthly run costs | C37: =SUM('Cash flow'!D5:D41) | D37: =SUM('Cash flow'!K5:K41) | E37: =SUM('Cash flow'!R5:R41)
A38: Simple ROI over 3 years | B38: (total benefit - total cost) / total cost | C38: =(C36-C37)/C37 | D38: =(D36-D37)/D37 | E38: =(E36-E37)/E37
A39: Not counted: value of saved hours not redeployed, per year | B39: for information only; not in NPV | C39: =(C25-C26)*C9*12*C21 | D39: =(D25-D26)*D9*12*D21 | E39: =(E25-E26)*E9*12*E21
A41: Hours are counted as cash only for the redeployed share. See the counting rules on 'Read me'.

Sheet Cash flow
A1: Monthly cash flow (36 months)
A2: UC-01: Supplier delivery notes captured into the ERP without manual typing
A3: FICTIONAL EXAMPLE. All names and figures are invented for illustration ("Northwind Aero Services"). | B3: Pessimistic | I3: Base | P3: Optimistic
A4: Month | B4: Adoption | C4: Benefit | D4: Cost | E4: Net | F4: Cumulative | G4: Discounted net | H4: Payback month | I4: Adoption | J4: Benefit | K4: Cost | L4: Net | M4: Cumulative | N4: Discounted net | O4: Payback month | P4: Adoption | Q4: Benefit | R4: Cost | S4: Net | T4: Cumulative | U4: Discounted net | V4: Payback month
A5: 0 | B5: =IF($A5=0,0,IF($A5<=Calculation!C$20,Calculation!C$19,Calculation!C$21)) | C5: =Calculation!C$30*B5 | D5: =IF($A5=0,Calculation!C$32,Calculation!C$33/12) | E5: =C5-D5 | F5: =E5 | G5: =E5/(1+Calculation!C$22)^($A5/12) | H5: ="" | I5: =IF($A5=0,0,IF($A5<=Calculation!D$20,Calculation!D$19,Calculation!D$21)) | J5: =Calculation!D$30*I5 | K5: =IF($A5=0,Calculation!D$32,Calculation!D$33/12) | L5: =J5-K5 | M5: =L5 | N5: =L5/(1+Calculation!D$22)^($A5/12) | O5: ="" | P5: =IF($A5=0,0,IF($A5<=Calculation!E$20,Calculation!E$19,Calculation!E$21)) | Q5: =Calculation!E$30*P5 | R5: =IF($A5=0,Calculation!E$32,Calculation!E$33/12) | S5: =Q5-R5 | T5: =S5 | U5: =S5/(1+Calculation!E$22)^($A5/12) | V5: =""
A6: 1 | B6: =IF($A6=0,0,IF($A6<=Calculation!C$20,Calculation!C$19,Calculation!C$21)) | C6: =Calculation!C$30*B6 | D6: =IF($A6=0,Calculation!C$32,Calculation!C$33/12) | E6: =C6-D6 | F6: =F5+E6 | G6: =E6/(1+Calculation!C$22)^($A6/12) | H6: =IF(AND(F6>=0,F5<0),$A6,"") | I6: =IF($A6=0,0,IF($A6<=Calculation!D$20,Calculation!D$19,Calculation!D$21)) | J6: =Calculation!D$30*I6 | K6: =IF($A6=0,Calculation!D$32,Calculation!D$33/12) | L6: =J6-K6 | M6: =M5+L6 | N6: =L6/(1+Calculation!D$22)^($A6/12) | O6: =IF(AND(M6>=0,M5<0),$A6,"") | P6: =IF($A6=0,0,IF($A6<=Calculation!E$20,Calculation!E$19,Calculation!E$21)) | Q6: =Calculation!E$30*P6 | R6: =IF($A6=0,Calculation!E$32,Calculation!E$33/12) | S6: =Q6-R6 | T6: =T5+S6 | U6: =S6/(1+Calculation!E$22)^($A6/12) | V6: =IF(AND(T6>=0,T5<0),$A6,"")
A7: 2 | B7: =IF($A7=0,0,IF($A7<=Calculation!C$20,Calculation!C$19,Calculation!C$21)) | C7: =Calculation!C$30*B7 | D7: =IF($A7=0,Calculation!C$32,Calculation!C$33/12) | E7: =C7-D7 | F7: =F6+E7 | G7: =E7/(1+Calculation!C$22)^($A7/12) | H7: =IF(AND(F7>=0,F6<0),$A7,"") | I7: =IF($A7=0,0,IF($A7<=Calculation!D$20,Calculation!D$19,Calculation!D$21)) | J7: =Calculation!D$30*I7 | K7: =IF($A7=0,Calculation!D$32,Calculation!D$33/12) | L7: =J7-K7 | M7: =M6+L7 | N7: =L7/(1+Calculation!D$22)^($A7/12) | O7: =IF(AND(M7>=0,M6<0),$A7,"") | P7: =IF($A7=0,0,IF($A7<=Calculation!E$20,Calculation!E$19,Calculation!E$21)) | Q7: =Calculation!E$30*P7 | R7: =IF($A7=0,Calculation!E$32,Calculation!E$33/12) | S7: =Q7-R7 | T7: =T6+S7 | U7: =S7/(1+Calculation!E$22)^($A7/12) | V7: =IF(AND(T7>=0,T6<0),$A7,"")
A8: 3 | B8: =IF($A8=0,0,IF($A8<=Calculation!C$20,Calculation!C$19,Calculation!C$21)) | C8: =Calculation!C$30*B8 | D8: =IF($A8=0,Calculation!C$32,Calculation!C$33/12) | E8: =C8-D8 | F8: =F7+E8 | G8: =E8/(1+Calculation!C$22)^($A8/12) | H8: =IF(AND(F8>=0,F7<0),$A8,"") | I8: =IF($A8=0,0,IF($A8<=Calculation!D$20,Calculation!D$19,Calculation!D$21)) | J8: =Calculation!D$30*I8 | K8: =IF($A8=0,Calculation!D$32,Calculation!D$33/12) | L8: =J8-K8 | M8: =M7+L8 | N8: =L8/(1+Calculation!D$22)^($A8/12) | O8: =IF(AND(M8>=0,M7<0),$A8,"") | P8: =IF($A8=0,0,IF($A8<=Calculation!E$20,Calculation!E$19,Calculation!E$21)) | Q8: =Calculation!E$30*P8 | R8: =IF($A8=0,Calculation!E$32,Calculation!E$33/12) | S8: =Q8-R8 | T8: =T7+S8 | U8: =S8/(1+Calculation!E$22)^($A8/12) | V8: =IF(AND(T8>=0,T7<0),$A8,"")
A9: 4 | B9: =IF($A9=0,0,IF($A9<=Calculation!C$20,Calculation!C$19,Calculation!C$21)) | C9: =Calculation!C$30*B9 | D9: =IF($A9=0,Calculation!C$32,Calculation!C$33/12) | E9: =C9-D9 | F9: =F8+E9 | G9: =E9/(1+Calculation!C$22)^($A9/12) | H9: =IF(AND(F9>=0,F8<0),$A9,"") | I9: =IF($A9=0,0,IF($A9<=Calculation!D$20,Calculation!D$19,Calculation!D$21)) | J9: =Calculation!D$30*I9 | K9: =IF($A9=0,Calculation!D$32,Calculation!D$33/12) | L9: =J9-K9 | M9: =M8+L9 | N9: =L9/(1+Calculation!D$22)^($A9/12) | O9: =IF(AND(M9>=0,M8<0),$A9,"") | P9: =IF($A9=0,0,IF($A9<=Calculation!E$20,Calculation!E$19,Calculation!E$21)) | Q9: =Calculation!E$30*P9 | R9: =IF($A9=0,Calculation!E$32,Calculation!E$33/12) | S9: =Q9-R9 | T9: =T8+S9 | U9: =S9/(1+Calculation!E$22)^($A9/12) | V9: =IF(AND(T9>=0,T8<0),$A9,"")
A10: 5 | B10: =IF($A10=0,0,IF($A10<=Calculation!C$20,Calculation!C$19,Calculation!C$21)) | C10: =Calculation!C$30*B10 | D10: =IF($A10=0,Calculation!C$32,Calculation!C$33/12) | E10: =C10-D10 | F10: =F9+E10 | G10: =E10/(1+Calculation!C$22)^($A10/12) | H10: =IF(AND(F10>=0,F9<0),$A10,"") | I10: =IF($A10=0,0,IF($A10<=Calculation!D$20,Calculation!D$19,Calculation!D$21)) | J10: =Calculation!D$30*I10 | K10: =IF($A10=0,Calculation!D$32,Calculation!D$33/12) | L10: =J10-K10 | M10: =M9+L10 | N10: =L10/(1+Calculation!D$22)^($A10/12) | O10: =IF(AND(M10>=0,M9<0),$A10,"") | P10: =IF($A10=0,0,IF($A10<=Calculation!E$20,Calculation!E$19,Calculation!E$21)) | Q10: =Calculation!E$30*P10 | R10: =IF($A10=0,Calculation!E$32,Calculation!E$33/12) | S10: =Q10-R10 | T10: =T9+S10 | U10: =S10/(1+Calculation!E$22)^($A10/12) | V10: =IF(AND(T10>=0,T9<0),$A10,"")
A11: 6 | B11: =IF($A11=0,0,IF($A11<=Calculation!C$20,Calculation!C$19,Calculation!C$21)) | C11: =Calculation!C$30*B11 | D11: =IF($A11=0,Calculation!C$32,Calculation!C$33/12) | E11: =C11-D11 | F11: =F10+E11 | G11: =E11/(1+Calculation!C$22)^($A11/12) | H11: =IF(AND(F11>=0,F10<0),$A11,"") | I11: =IF($A11=0,0,IF($A11<=Calculation!D$20,Calculation!D$19,Calculation!D$21)) | J11: =Calculation!D$30*I11 | K11: =IF($A11=0,Calculation!D$32,Calculation!D$33/12) | L11: =J11-K11 | M11: =M10+L11 | N11: =L11/(1+Calculation!D$22)^($A11/12) | O11: =IF(AND(M11>=0,M10<0),$A11,"") | P11: =IF($A11=0,0,IF($A11<=Calculation!E$20,Calculation!E$19,Calculation!E$21)) | Q11: =Calculation!E$30*P11 | R11: =IF($A11=0,Calculation!E$32,Calculation!E$33/12) | S11: =Q11-R11 | T11: =T10+S11 | U11: =S11/(1+Calculation!E$22)^($A11/12) | V11: =IF(AND(T11>=0,T10<0),$A11,"")
A12: 7 | B12: =IF($A12=0,0,IF($A12<=Calculation!C$20,Calculation!C$19,Calculation!C$21)) | C12: =Calculation!C$30*B12 | D12: =IF($A12=0,Calculation!C$32,Calculation!C$33/12) | E12: =C12-D12 | F12: =F11+E12 | G12: =E12/(1+Calculation!C$22)^($A12/12) | H12: =IF(AND(F12>=0,F11<0),$A12,"") | I12: =IF($A12=0,0,IF($A12<=Calculation!D$20,Calculation!D$19,Calculation!D$21)) | J12: =Calculation!D$30*I12 | K12: =IF($A12=0,Calculation!D$32,Calculation!D$33/12) | L12: =J12-K12 | M12: =M11+L12 | N12: =L12/(1+Calculation!D$22)^($A12/12) | O12: =IF(AND(M12>=0,M11<0),$A12,"") | P12: =IF($A12=0,0,IF($A12<=Calculation!E$20,Calculation!E$19,Calculation!E$21)) | Q12: =Calculation!E$30*P12 | R12: =IF($A12=0,Calculation!E$32,Calculation!E$33/12) | S12: =Q12-R12 | T12: =T11+S12 | U12: =S12/(1+Calculation!E$22)^($A12/12) | V12: =IF(AND(T12>=0,T11<0),$A12,"")
A13: 8 | B13: =IF($A13=0,0,IF($A13<=Calculation!C$20,Calculation!C$19,Calculation!C$21)) | C13: =Calculation!C$30*B13 | D13: =IF($A13=0,Calculation!C$32,Calculation!C$33/12) | E13: =C13-D13 | F13: =F12+E13 | G13: =E13/(1+Calculation!C$22)^($A13/12) | H13: =IF(AND(F13>=0,F12<0),$A13,"") | I13: =IF($A13=0,0,IF($A13<=Calculation!D$20,Calculation!D$19,Calculation!D$21)) | J13: =Calculation!D$30*I13 | K13: =IF($A13=0,Calculation!D$32,Calculation!D$33/12) | L13: =J13-K13 | M13: =M12+L13 | N13: =L13/(1+Calculation!D$22)^($A13/12) | O13: =IF(AND(M13>=0,M12<0),$A13,"") | P13: =IF($A13=0,0,IF($A13<=Calculation!E$20,Calculation!E$19,Calculation!E$21)) | Q13: =Calculation!E$30*P13 | R13: =IF($A13=0,Calculation!E$32,Calculation!E$33/12) | S13: =Q13-R13 | T13: =T12+S13 | U13: =S13/(1+Calculation!E$22)^($A13/12) | V13: =IF(AND(T13>=0,T12<0),$A13,"")
A14: 9 | B14: =IF($A14=0,0,IF($A14<=Calculation!C$20,Calculation!C$19,Calculation!C$21)) | C14: =Calculation!C$30*B14 | D14: =IF($A14=0,Calculation!C$32,Calculation!C$33/12) | E14: =C14-D14 | F14: =F13+E14 | G14: =E14/(1+Calculation!C$22)^($A14/12) | H14: =IF(AND(F14>=0,F13<0),$A14,"") | I14: =IF($A14=0,0,IF($A14<=Calculation!D$20,Calculation!D$19,Calculation!D$21)) | J14: =Calculation!D$30*I14 | K14: =IF($A14=0,Calculation!D$32,Calculation!D$33/12) | L14: =J14-K14 | M14: =M13+L14 | N14: =L14/(1+Calculation!D$22)^($A14/12) | O14: =IF(AND(M14>=0,M13<0),$A14,"") | P14: =IF($A14=0,0,IF($A14<=Calculation!E$20,Calculation!E$19,Calculation!E$21)) | Q14: =Calculation!E$30*P14 | R14: =IF($A14=0,Calculation!E$32,Calculation!E$33/12) | S14: =Q14-R14 | T14: =T13+S14 | U14: =S14/(1+Calculation!E$22)^($A14/12) | V14: =IF(AND(T14>=0,T13<0),$A14,"")
A15: 10 | B15: =IF($A15=0,0,IF($A15<=Calculation!C$20,Calculation!C$19,Calculation!C$21)) | C15: =Calculation!C$30*B15 | D15: =IF($A15=0,Calculation!C$32,Calculation!C$33/12) | E15: =C15-D15 | F15: =F14+E15 | G15: =E15/(1+Calculation!C$22)^($A15/12) | H15: =IF(AND(F15>=0,F14<0),$A15,"") | I15: =IF($A15=0,0,IF($A15<=Calculation!D$20,Calculation!D$19,Calculation!D$21)) | J15: =Calculation!D$30*I15 | K15: =IF($A15=0,Calculation!D$32,Calculation!D$33/12) | L15: =J15-K15 | M15: =M14+L15 | N15: =L15/(1+Calculation!D$22)^($A15/12) | O15: =IF(AND(M15>=0,M14<0),$A15,"") | P15: =IF($A15=0,0,IF($A15<=Calculation!E$20,Calculation!E$19,Calculation!E$21)) | Q15: =Calculation!E$30*P15 | R15: =IF($A15=0,Calculation!E$32,Calculation!E$33/12) | S15: =Q15-R15 | T15: =T14+S15 | U15: =S15/(1+Calculation!E$22)^($A15/12) | V15: =IF(AND(T15>=0,T14<0),$A15,"")
A16: 11 | B16: =IF($A16=0,0,IF($A16<=Calculation!C$20,Calculation!C$19,Calculation!C$21)) | C16: =Calculation!C$30*B16 | D16: =IF($A16=0,Calculation!C$32,Calculation!C$33/12) | E16: =C16-D16 | F16: =F15+E16 | G16: =E16/(1+Calculation!C$22)^($A16/12) | H16: =IF(AND(F16>=0,F15<0),$A16,"") | I16: =IF($A16=0,0,IF($A16<=Calculation!D$20,Calculation!D$19,Calculation!D$21)) | J16: =Calculation!D$30*I16 | K16: =IF($A16=0,Calculation!D$32,Calculation!D$33/12) | L16: =J16-K16 | M16: =M15+L16 | N16: =L16/(1+Calculation!D$22)^($A16/12) | O16: =IF(AND(M16>=0,M15<0),$A16,"") | P16: =IF($A16=0,0,IF($A16<=Calculation!E$20,Calculation!E$19,Calculation!E$21)) | Q16: =Calculation!E$30*P16 | R16: =IF($A16=0,Calculation!E$32,Calculation!E$33/12) | S16: =Q16-R16 | T16: =T15+S16 | U16: =S16/(1+Calculation!E$22)^($A16/12) | V16: =IF(AND(T16>=0,T15<0),$A16,"")
A17: 12 | B17: =IF($A17=0,0,IF($A17<=Calculation!C$20,Calculation!C$19,Calculation!C$21)) | C17: =Calculation!C$30*B17 | D17: =IF($A17=0,Calculation!C$32,Calculation!C$33/12) | E17: =C17-D17 | F17: =F16+E17 | G17: =E17/(1+Calculation!C$22)^($A17/12) | H17: =IF(AND(F17>=0,F16<0),$A17,"") | I17: =IF($A17=0,0,IF($A17<=Calculation!D$20,Calculation!D$19,Calculation!D$21)) | J17: =Calculation!D$30*I17 | K17: =IF($A17=0,Calculation!D$32,Calculation!D$33/12) | L17: =J17-K17 | M17: =M16+L17 | N17: =L17/(1+Calculation!D$22)^($A17/12) | O17: =IF(AND(M17>=0,M16<0),$A17,"") | P17: =IF($A17=0,0,IF($A17<=Calculation!E$20,Calculation!E$19,Calculation!E$21)) | Q17: =Calculation!E$30*P17 | R17: =IF($A17=0,Calculation!E$32,Calculation!E$33/12) | S17: =Q17-R17 | T17: =T16+S17 | U17: =S17/(1+Calculation!E$22)^($A17/12) | V17: =IF(AND(T17>=0,T16<0),$A17,"")
... A41: 36 | B41: =IF($A41=0,0,IF($A41<=Calculation!C$20,Calculation!C$19,Calculation!C$21)) | C41: =Calculation!C$30*B41 | D41: =IF($A41=0,Calculation!C$32,Calculation!C$33/12) | E41: =C41-D41 | F41: =F40+E41 | G41: =E41/(1+Calculation!C$22)^($A41/12) | H41: =IF(AND(F41>=0,F40<0),$A41,"") | I41: =IF($A41=0,0,IF($A41<=Calculation!D$20,Calculation!D$19,Calculation!D$21)) | J41: =Calculation!D$30*I41 | K41: =IF($A41=0,Calculation!D$32,Calculation!D$33/12) | L41: =J41-K41 | M41: =M40+L41 | N41: =L41/(1+Calculation!D$22)^($A41/12) | O41: =IF(AND(M41>=0,M40<0),$A41,"") | P41: =IF($A41=0,0,IF($A41<=Calculation!E$20,Calculation!E$19,Calculation!E$21)) | Q41: =Calculation!E$30*P41 | R41: =IF($A41=0,Calculation!E$32,Calculation!E$33/12) | S41: =Q41-R41 | T41: =T40+S41 | U41: =S41/(1+Calculation!E$22)^($A41/12) | V41: =IF(AND(T41>=0,T40<0),$A41,"")

Sheet Assumptions log
A1: Assumptions log
A2: UC-01: Supplier delivery notes captured into the ERP without manual typing
A3: FICTIONAL EXAMPLE. All names and figures are invented for illustration ("Northwind Aero Services").
A4: ID | B4: Input | C4: Value (base) | D4: Unit | E4: Source or reasoning | F4: Confidence | G4: Scenario range
A5: volume_per_month | B5: Transactions per month | C5: =volume_per_month | D5: delivery notes / month | E5: Goods-receipt log, 12-month average (fictional). | F5: high
A6: minutes_before | B6: Handling time per transaction today | C6: =minutes_before | D6: minutes | E6: Time study on a sample of 50 notes (fictional). | F6: medium
A7: minutes_after | B7: Handling time per transaction with the AI solution | C7: =minutes_after | D7: minutes | E7: Vendor demo on 30 sample notes; clerk checks and confirms each pre-filled receipt. | F7: low | G7: 3 / base / 1.5
A8: hourly_cost_eur | B8: Fully loaded cost per hour | C8: =hourly_cost_eur | D8: EUR / hour | E8: Controlling standard rate (fictional), including salary, social charges and overhead. | F8: high
A9: share_hours_redeployed | B9: Share of saved hours redeployed or avoiding a cost | C9: =share_hours_redeployed | D9: share (0-1) | E9: Process owner plan to move time to the backlog of supplier claims; the rest is absorbed and not counted as cash. | F9: low | G9: 0.25 / base / 0.75
A10: error_rate_before | B10: Error rate today | C10: =error_rate_before | D10: share of transactions | E10: Stock-count findings traced to keying errors (fictional). | F10: medium
A11: error_rate_after | B11: Error rate with the AI solution | C11: =error_rate_after | D11: share of transactions | E11: Remaining errors from low-confidence fields the clerk does not catch; estimate. | F11: medium
A12: cost_per_error_eur | B12: Cost per error | C12: =cost_per_error_eur | D12: EUR / error | E12: Rework time plus stock correction, estimated by the process owner. | F12: medium
A13: licence_cost_per_year_eur | B13: Licence cost per year | C13: =licence_cost_per_year_eur | D13: EUR / year | E13: Indicative vendor quote for the document volume (fictional). | F13: high
A14: build_days | B14: Internal build effort | C14: =build_days | D14: person-days | E14: IT estimate for interface, configuration, testing and key-user time. | F14: medium
A15: day_rate_eur | B15: Internal day rate | C15: =day_rate_eur | D15: EUR / day | E15: Controlling internal rate (fictional). | F15: high
A16: other_one_off_eur | B16: Other one-off costs | C16: =other_one_off_eur | D16: EUR | E16: Training, change management and an external integration partner. | F16: medium
A17: run_cost_per_year_eur | B17: Run cost per year | C17: =run_cost_per_year_eur | D17: EUR / year | E17: Hosting, monitoring, support and a monthly quality sample. | F17: medium
A18: adoption_initial | B18: Adoption during the ramp-up | C18: =adoption_initial | D18: share of volume | E18: Typical first-quarter adoption; only PDF notes from the largest suppliers at first. | F18: medium
A19: ramp_months | B19: Length of the ramp-up | C19: =ramp_months | D19: months | E19: Roll-out plan. | F19: medium
A20: adoption_steady | B20: Adoption after the ramp-up | C20: =adoption_steady | D20: share of volume | E20: About 20% of notes are handwritten or unusual layouts and stay manual. | F20: low | G20: 0.6 / base / 0.9
A21: discount_rate | B21: Discount rate | C21: =discount_rate | D21: per year | E21: Finance standard rate for internal projects (fictional). | F21: high
